odoo/addons/website_breadcrumb/README.rst
odoo/addons/website_breadcrumb/__init__.py
odoo/addons/website_breadcrumb/__manifest__.py
odoo/addons/website_breadcrumb/i18n/ar.po
odoo/addons/website_breadcrumb/i18n/ca.po
odoo/addons/website_breadcrumb/i18n/de.po
odoo/addons/website_breadcrumb/i18n/el.po
odoo/addons/website_breadcrumb/i18n/el_GR.po
odoo/addons/website_breadcrumb/i18n/es.po
odoo/addons/website_breadcrumb/i18n/es_CR.po
odoo/addons/website_breadcrumb/i18n/es_MX.po
odoo/addons/website_breadcrumb/i18n/es_VE.po
odoo/addons/website_breadcrumb/i18n/fi.po
odoo/addons/website_breadcrumb/i18n/fr.po
odoo/addons/website_breadcrumb/i18n/gl.po
odoo/addons/website_breadcrumb/i18n/hr.po
odoo/addons/website_breadcrumb/i18n/hu.po
odoo/addons/website_breadcrumb/i18n/it.po
odoo/addons/website_breadcrumb/i18n/ja.po
odoo/addons/website_breadcrumb/i18n/lt.po
odoo/addons/website_breadcrumb/i18n/lv.po
odoo/addons/website_breadcrumb/i18n/mk.po
odoo/addons/website_breadcrumb/i18n/mn.po
odoo/addons/website_breadcrumb/i18n/nl.po
odoo/addons/website_breadcrumb/i18n/pl.po
odoo/addons/website_breadcrumb/i18n/pt.po
odoo/addons/website_breadcrumb/i18n/pt_BR.po
odoo/addons/website_breadcrumb/i18n/ro.po
odoo/addons/website_breadcrumb/i18n/ru.po
odoo/addons/website_breadcrumb/i18n/sl.po
odoo/addons/website_breadcrumb/i18n/sv.po
odoo/addons/website_breadcrumb/i18n/website_breadcrumb.pot
odoo/addons/website_breadcrumb/i18n/zh_CN.po
odoo/addons/website_breadcrumb/models/__init__.py
odoo/addons/website_breadcrumb/models/website.py
odoo/addons/website_breadcrumb/readme/CONFIGURE.rst
odoo/addons/website_breadcrumb/readme/CONTRIBUTORS.rst
odoo/addons/website_breadcrumb/readme/DESCRIPTION.rst
odoo/addons/website_breadcrumb/readme/USAGE.rst
odoo/addons/website_breadcrumb/static/description/icon.png
odoo/addons/website_breadcrumb/static/description/icon.svg
odoo/addons/website_breadcrumb/static/description/index.html
odoo/addons/website_breadcrumb/views/layout.xml
odoo13_addon_website_breadcrumb-13.0.1.0.1.dist-info/METADATA
odoo13_addon_website_breadcrumb-13.0.1.0.1.dist-info/WHEEL
odoo13_addon_website_breadcrumb-13.0.1.0.1.dist-info/top_level.txt
odoo13_addon_website_breadcrumb-13.0.1.0.1.dist-info/RECORD
